pyft4222/__init__.py
pyft4222/gpio.py
pyft4222/handle.py
pyft4222/py.typed
pyft4222/result.py
pyft4222/stream.py
pyft4222/i2c/__init__.py
pyft4222/i2c/master.py
pyft4222/i2c/slave.py
pyft4222/spi/__init__.py
pyft4222/spi/common.py
pyft4222/spi/master.py
pyft4222/spi/slave.py
pyft4222/wrapper/__init__.py
pyft4222/wrapper/common.py
pyft4222/wrapper/dll_loader.py
pyft4222/wrapper/ftd2xx.py
pyft4222/wrapper/gpio.py
pyft4222/wrapper/dll/__init__.py
pyft4222/wrapper/dll/linux/__init__.py
pyft4222/wrapper/dll/linux/aarch64/__init__.py
pyft4222/wrapper/dll/linux/aarch64/libft4222.so.1.4.4.232
pyft4222/wrapper/dll/linux/amd64/__init__.py
pyft4222/wrapper/dll/linux/amd64/libft4222.so.1.4.4.232
pyft4222/wrapper/dll/osx/__init__.py
pyft4222/wrapper/dll/osx/universal/__init__.py
pyft4222/wrapper/dll/osx/universal/libft4222.1.4.4.221.dylib
pyft4222/wrapper/dll/win/__init__.py
pyft4222/wrapper/dll/win/amd64/LibFT4222-64.dll
pyft4222/wrapper/dll/win/amd64/__init__.py
pyft4222/wrapper/dll/win/arm64/LibFT4222-64.dll
pyft4222/wrapper/dll/win/arm64/__init__.py
pyft4222/wrapper/i2c/__init__.py
pyft4222/wrapper/i2c/master.py
pyft4222/wrapper/i2c/slave.py
pyft4222/wrapper/spi/__init__.py
pyft4222/wrapper/spi/common.py
pyft4222/wrapper/spi/master.py
pyft4222/wrapper/spi/slave.py
pyft4222-0.3.3.dist-info/METADATA
pyft4222-0.3.3.dist-info/WHEEL
pyft4222-0.3.3.dist-info/licenses/LICENSE
pyft4222-0.3.3.dist-info/RECORD
