Metadata-Version: 2.4
Name: pyft4222
Version: 0.3.3
Summary: A python wrapper for libft4222 library
Project-URL: Homepage, https://github.com/lavovaLampa/pyft4222
Project-URL: Issues, https://github.com/lavovaLampa/pyft4222/issues
Author-email: Martin Cizmar <lavovalampa@protonmail.com>
License-Expression: MIT
License-File: LICENSE
Classifier: Development Status :: 4 - Beta
Classifier: Environment :: Console
Classifier: Intended Audience :: Developers
Classifier: License :: OSI Approved :: MIT License
Classifier: Operating System :: Microsoft :: Windows
Classifier: Operating System :: POSIX :: Linux
Classifier: Programming Language :: Python :: 3
Classifier: Programming Language :: Python :: 3.9
Classifier: Programming Language :: Python :: 3.10
Classifier: Programming Language :: Python :: 3.11
Classifier: Programming Language :: Python :: 3.12
Requires-Python: >=3.9
Requires-Dist: typing-extensions
